redmine_loader/__init__.py
redmine_loader/loader.py
redmine_loader/models.py
redmine_loader-0.1.1.dist-info/LICENSE
redmine_loader-0.1.1.dist-info/METADATA
redmine_loader-0.1.1.dist-info/WHEEL
redmine_loader-0.1.1.dist-info/RECORD
