Metadata-Version: 2.1
Name: redmine-loader
Version: 0.1.1
Summary: Document Loader for bitnami Redmine. Crawl Redmine Issues using WebAPI and gather issue subject, description, comments, attachments. Attachments are parsed with unstructured.io .
License: MIT
Author: syakesaba
Author-email: pakemon@syakesaba.com
Requires-Python: >=3.11,<=3.12
Classifier: License :: OSI Approved :: MIT License
Classifier: Programming Language :: Python :: 3
Classifier: Programming Language :: Python :: 3.11
Classifier: Programming Language :: Python :: 3.12
Requires-Dist: httpx (>=0.27.2,<0.28.0)
Requires-Dist: langchain (>=0.3.0,<0.4.0)
Requires-Dist: langchain-community (>=0.3.0,<0.4.0)
Requires-Dist: langchain-unstructured[local-inference] (>=0.1.4,<0.2.0)
Requires-Dist: pydantic (>=2.9.2,<3.0.0)
Requires-Dist: unstructured (>=0.15.12,<0.16.0)
